iot/samba/client/__init__.py
iot/samba/client/_client.py
iot/samba/client/_version.py
iot_samba_client-1.0.5.dist-info/METADATA
iot_samba_client-1.0.5.dist-info/WHEEL
iot_samba_client-1.0.5.dist-info/top_level.txt
iot_samba_client-1.0.5.dist-info/RECORD
