Metadata-Version: 2.1
Name: iot-samba-client
Version: 1.0.5
Summary: IoT Samba Client Library for Python
Author: Dylan Gonzales
Author-email: py.iot.utils@gmail.com
License: MIT License
Classifier: Programming Language :: Python :: 3 :: Only
Classifier: Programming Language :: Python :: 3
Classifier: Programming Language :: Python :: 3.7
Classifier: Programming Language :: Python :: 3.8
Classifier: Programming Language :: Python :: 3.9
Classifier: Programming Language :: Python :: 3.10
Classifier: License :: OSI Approved :: MIT License
Requires-Python: >=3.7
Requires-Dist: smbprotocol (==1.9.0)
Requires-Dist: pydantic (==1.9.0)
